<?xml version="1.0" encoding="utf-8"?>
<IncrementalBankBuild Version="6" Flags="601859981">
	<Platform GUID="{07A3DDE0-8971-4970-919F-6EB78178D475}">
		<Banks>
			<Language ID="0">
				<File Name="Init" Hash="3817634215" Timestamp="131552734144396965"/>
				<File Name="MRBook" Hash="1718115638" Timestamp="131552965815037276"/>
			</Language>
		</Banks>
		<XMLInfo>
			<Language ID="-1">
				<File Name="" Hash="2751794517" Timestamp="131552965815092470"/>
			</Language>
		</XMLInfo>
	</Platform>
</IncrementalBankBuild>
